<annotation>
	<folder>img</folder>
	<filename>fuel_tank_LH12735.jpg</filename>
	<path>/media/dinesh/Disk_Data/Rams_WFH/img/fuel_tank_LH12735.jpg</path>
	<source>
		<database>Unknown</database>
	</source>
	<size>
		<width>1920</width>
		<height>1080</height>
		<depth>3</depth>
	</size>
	<segmented>0</segmented>
	<object>
		<name>fuel_tank_danger_sticker</name>
		<pose>Unspecified</pose>
		<truncated>0</truncated>
		<difficult>0</difficult>
		<bndbox>
			<xmin>1540</xmin>
			<ymin>512</ymin>
			<xmax>1695</xmax>
			<ymax>745</ymax>
		</bndbox>
	</object>
	<object>
		<name>fuel_tank</name>
		<pose>Unspecified</pose>
		<truncated>0</truncated>
		<difficult>0</difficult>
		<bndbox>
			<xmin>1122</xmin>
			<ymin>260</ymin>
			<xmax>1515</xmax>
			<ymax>569</ymax>
		</bndbox>
	</object>
</annotation>
